JingtongTensorflow1XChuyi/README.md
JingtongTensorflow1XChuyi/__init__.py
JingtongTensorflow1XChuyi/__main__.py
JingtongTensorflow1XChuyi/file.epub
JingtongTensorflow1XChuyi/index.html
JingtongTensorflow1XChuyi/css/__init__.py
JingtongTensorflow1XChuyi/css/annotations.css
JingtongTensorflow1XChuyi/css/main.css
JingtongTensorflow1XChuyi/css/normalize.css
JingtongTensorflow1XChuyi/css/popup.css
JingtongTensorflow1XChuyi/font/__init__.py
JingtongTensorflow1XChuyi/font/fontello.eot
JingtongTensorflow1XChuyi/font/fontello.svg
JingtongTensorflow1XChuyi/font/fontello.ttf
JingtongTensorflow1XChuyi/font/fontello.woff
JingtongTensorflow1XChuyi/img/__init__.py
JingtongTensorflow1XChuyi/img/annotator-glyph-sprite.png
JingtongTensorflow1XChuyi/img/annotator-icon-sprite.png
JingtongTensorflow1XChuyi/img/apple-touch-icon.png
JingtongTensorflow1XChuyi/img/cancelfullscreen.png
JingtongTensorflow1XChuyi/img/close.png
JingtongTensorflow1XChuyi/img/fullscreen.png
JingtongTensorflow1XChuyi/img/loader.gif
JingtongTensorflow1XChuyi/img/menu-icon.png
JingtongTensorflow1XChuyi/img/save.png
JingtongTensorflow1XChuyi/img/saved.png
JingtongTensorflow1XChuyi/img/settings-s.png
JingtongTensorflow1XChuyi/img/settings.png
JingtongTensorflow1XChuyi/img/star.png
JingtongTensorflow1XChuyi/js/__init__.py
JingtongTensorflow1XChuyi/js/epub.js
JingtongTensorflow1XChuyi/js/epub.min.js
JingtongTensorflow1XChuyi/js/epub.min.map
JingtongTensorflow1XChuyi/js/hooks.min.js
JingtongTensorflow1XChuyi/js/hooks.min.map
JingtongTensorflow1XChuyi/js/reader.js
JingtongTensorflow1XChuyi/js/reader.js.map
JingtongTensorflow1XChuyi/js/reader.min.js
JingtongTensorflow1XChuyi/js/reader.min.map
JingtongTensorflow1XChuyi/js/hooks/__init__.py
JingtongTensorflow1XChuyi/js/hooks/extensions/__init__.py
JingtongTensorflow1XChuyi/js/hooks/extensions/highlight.js
JingtongTensorflow1XChuyi/js/libs/__init__.py
JingtongTensorflow1XChuyi/js/libs/jquery.min.js
JingtongTensorflow1XChuyi/js/libs/localforage.min.js
jingtong_tensorflow_1_x_chuyi-2024.3.5.0.dist-info/METADATA
jingtong_tensorflow_1_x_chuyi-2024.3.5.0.dist-info/WHEEL
jingtong_tensorflow_1_x_chuyi-2024.3.5.0.dist-info/entry_points.txt
jingtong_tensorflow_1_x_chuyi-2024.3.5.0.dist-info/top_level.txt
jingtong_tensorflow_1_x_chuyi-2024.3.5.0.dist-info/RECORD
